atomistic/__init__.py
atomistic/_version.py
atomistic/atomistic.py
atomistic/bicrystal.py
atomistic/bulk.py
atomistic/crystal.py
atomistic/mathsutils.py
atomistic/tensile_test.py
atomistic/utils.py
atomistic/visualise.py
atomistic/voronoi.py
atomistic/api/__init__.py
atomistic/api/bicrystal.py
atomistic/data/jmol_colours.pickle
atomistic/data/jmol_colours.txt
atomistic-0.3.4.dist-info/LICENSE
atomistic-0.3.4.dist-info/METADATA
atomistic-0.3.4.dist-info/WHEEL
atomistic-0.3.4.dist-info/top_level.txt
atomistic-0.3.4.dist-info/RECORD
