Metadata-Version: 2.1
Name: atomistic
Version: 0.3.4
Summary: Build atomistic structures such as grain boundaries with Python
Home-page: UNKNOWN
Author: Adam J. Plowman
Author-email: adam.plowman@manchester.ac.uk
License: UNKNOWN
Project-URL: Github, https://github.com/aplowman/atomistic
Platform: UNKNOWN
Classifier: Development Status :: 4 - Beta
Classifier: Intended Audience :: Science/Research
Classifier: Topic :: Scientific/Engineering
Classifier: Programming Language :: Python :: 3.5
Classifier: Programming Language :: Python :: 3.6
Classifier: Programming Language :: Python :: 3.7
Classifier: License :: OSI Approved :: Mozilla Public License 2.0 (MPL 2.0)
Classifier: Operating System :: OS Independent
Requires-Dist: numpy
Requires-Dist: scipy
Requires-Dist: gemo
Requires-Dist: vecmaths
Requires-Dist: bravais
Requires-Dist: mendeleev (==0.4.5)
Requires-Dist: spglib
Requires-Dist: beautifultable
Requires-Dist: progress
